cocotb2_migrator/__init__.py
cocotb2_migrator/cli.py
cocotb2_migrator/main.py
cocotb2_migrator/migrator.py
cocotb2_migrator/parser.py
cocotb2_migrator/report.py
cocotb2_migrator/transformers/__init__.py
cocotb2_migrator/transformers/base.py
cocotb2_migrator/transformers/binaryvalue_transformer.py
cocotb2_migrator/transformers/clock_transformer.py
cocotb2_migrator/transformers/coroutine_transformer.py
cocotb2_migrator/transformers/deprecated_imports_transformer.py
cocotb2_migrator/transformers/environment_transformer.py
cocotb2_migrator/transformers/fork_transformer.py
cocotb2_migrator/transformers/handle_transformer.py
cocotb2_migrator/transformers/join_transformer.py
cocotb2_migrator/transformers/logicarray_transformer.py
cocotb2_migrator/transformers/task_transformer.py
scripts/__init__.py
scripts/run_migration.py
tests/__init__.py
tests/test_binaryvalue_transformer.py
tests/test_clock_transformer.py
tests/test_coroutine_transformer.py
tests/test_deprecated_imports_transformer.py
tests/test_environment_transformer.py
tests/test_fork_transformer.py
tests/test_handle_transformer.py
tests/test_join_transformer.py
tests/test_logicarray_transformer.py
tests/test_parser.py
tests/test_report.py
tests/test_task_transformer.py
cocotb2_migrator-0.2.2.dist-info/METADATA
cocotb2_migrator-0.2.2.dist-info/WHEEL
cocotb2_migrator-0.2.2.dist-info/entry_points.txt
cocotb2_migrator-0.2.2.dist-info/top_level.txt
cocotb2_migrator-0.2.2.dist-info/RECORD
