Metadata-Version: 2.4
Name: cocotb2-migrator
Version: 0.2.2
Summary: Tool to migrate cocotb 1.x tests to cocotb 2.x style
Author-email: Aayush Gid <aayushgid598@gmail.com>
License: MIT
Project-URL: Homepage, https://pypi.org/project/cocotb2-migrator/
Project-URL: Repository, https://github.com/aayush598/cocotb2-migrator.git
Requires-Python: >=3.7
Requires-Dist: libcst
Requires-Dist: click
Requires-Dist: termcolor
Requires-Dist: rich
Dynamic: requires-python
